iceberg_loader/__about__.py
iceberg_loader/__init__.py
iceberg_loader/core/__init__.py
iceberg_loader/core/config.py
iceberg_loader/core/loader.py
iceberg_loader/core/partitioning.py
iceberg_loader/core/schema.py
iceberg_loader/core/strategies.py
iceberg_loader/iceberg_loader.py
iceberg_loader/py.typed
iceberg_loader/services/__init__.py
iceberg_loader/services/logging.py
iceberg_loader/services/maintenance.py
iceberg_loader/utils/__init__.py
iceberg_loader/utils/arrow.py
iceberg_loader/utils/types.py
iceberg_loader-0.1.2.dist-info/WHEEL
iceberg_loader-0.1.2.dist-info/METADATA
iceberg_loader-0.1.2.dist-info/RECORD
