Metadata-Version: 2.4
Name: iceberg-loader
Version: 0.1.2
Summary: A convenience wrapper around PyIceberg for simplified data loading into Apache Iceberg tables
Keywords: iceberg,arrow,etl,pyarrow,data-loading,schema-evolution,upsert
Author: Ivan Matveev
Author-email: Ivan Matveev <vndvtech@gmail.com>
License-Expression: MIT
Classifier: Development Status :: 4 - Beta
Classifier: License :: OSI Approved :: MIT License
Classifier: Typing :: Typed
Classifier: Programming Language :: Python
Classifier: Programming Language :: Python :: 3.10
Classifier: Programming Language :: Python :: 3.11
Classifier: Programming Language :: Python :: 3.12
Classifier: Programming Language :: Python :: 3.13
Classifier: Programming Language :: Python :: 3.14
Classifier: Programming Language :: Python :: Implementation :: CPython
Classifier: Operating System :: OS Independent
Classifier: Topic :: Database
Classifier: Topic :: Software Development :: Libraries :: Python Modules
Requires-Dist: pyarrow>=18.0.0
Requires-Dist: pyiceberg>=0.7.1
Requires-Dist: pyiceberg[hive,s3fs,pyiceberg-core]>=0.7.1 ; extra == 'all'
Requires-Dist: ruff>=0.5.0 ; extra == 'dev'
Requires-Dist: mypy>=1.10.0 ; extra == 'dev'
Requires-Dist: pytest>=7.0 ; extra == 'dev'
Requires-Dist: pytest-cov>=4.0 ; extra == 'dev'
Requires-Dist: pre-commit>=3.5.0 ; extra == 'dev'
Requires-Dist: twine>=5.0.0 ; extra == 'dev'
Requires-Dist: tox>=4.32.0 ; extra == 'dev'
Requires-Dist: pyiceberg[hive]>=0.7.1 ; extra == 'hive'
Requires-Dist: pyiceberg[s3fs]>=0.7.1 ; extra == 's3'
Requires-Dist: pytest>=7.0 ; extra == 'test'
Requires-Dist: pytest-cov>=4.0 ; extra == 'test'
Requires-Python: >=3.10
Project-URL: Bug Tracker, https://github.com/vndvtech/iceberg-loader/issues
Project-URL: Changelog, https://github.com/vndvtech/iceberg-loader/releases
Project-URL: Documentation, https://github.com/vndvtech/iceberg-loader
Project-URL: Homepage, https://github.com/vndvtech/iceberg-loader
Project-URL: Repository, https://github.com/vndvtech/iceberg-loader
Provides-Extra: all
Provides-Extra: dev
Provides-Extra: hive
Provides-Extra: s3
Provides-Extra: test
